initproject/__init__.py
initproject/__main__.py
initproject/__version__.py
initproject/core.py
initproject/include/.gitignore
initproject/include/initproject.code-workspace
initproject/include/settings.json
initproject-0.0.6.dist-info/METADATA
initproject-0.0.6.dist-info/RECORD
initproject-0.0.6.dist-info/WHEEL
initproject-0.0.6.dist-info/top_level.txt
