Metadata-Version: 2.1
Name: initproject
Version: 0.0.6
Summary: Initiate a blank python project
Home-page: https://github.com/superlevure/initproject
Author: Laurent Riviere
Author-email: laurent.riviere.pro@gmail.com
License: MIT
Platform: UNKNOWN
Classifier: License :: OSI Approved :: MIT License
Classifier: Programming Language :: Python
Classifier: Programming Language :: Python :: 3
Classifier: Programming Language :: Python :: 3.6
Classifier: Programming Language :: Python :: Implementation :: CPython
Classifier: Programming Language :: Python :: Implementation :: PyPy
Requires-Python: >=3.6.0
